py_ascii_tree/__init__.py
py_ascii_tree/core.py
py_ascii_tree/py.typed
py_ascii_tree/tests/test_core.py
py_ascii_tree-0.2.0.dist-info/licenses/LICENSE
py_ascii_tree-0.2.0.dist-info/METADATA
py_ascii_tree-0.2.0.dist-info/WHEEL
py_ascii_tree-0.2.0.dist-info/top_level.txt
py_ascii_tree-0.2.0.dist-info/RECORD
