Metadata-Version: 2.4
Name: py-ascii-tree
Version: 0.2.0
Summary: String ASCII tree from list or directory of filepaths
Author-email: Eva Maxfield Brown <evamaxfieldbrown@gmail.com>
License: MPLv2 License
Project-URL: Homepage, https://github.com/evamaxfield/py-ascii-tree
Project-URL: Bug Tracker, https://github.com/evamaxfield/py-ascii-tree/issues
Project-URL: Documentation, https://evamaxfield.github.io/py-ascii-tree
Project-URL: User Support, https://github.com/evamaxfield/py-ascii-tree/issues
Classifier: Development Status :: 4 - Beta
Classifier: Natural Language :: English
Classifier: Programming Language :: Python :: 3.10
Classifier: Programming Language :: Python :: 3.11
Classifier: Programming Language :: Python :: 3.12
Requires-Python: >=3.10
License-File: LICENSE
Provides-Extra: lint
Requires-Dist: pre-commit>=2.20.0; extra == "lint"
Provides-Extra: dev
Requires-Dist: ipython; extra == "dev"
Requires-Dist: jupyterlab; extra == "dev"
Provides-Extra: test
Requires-Dist: pytest<9,>=8; extra == "test"
Dynamic: license-file
